nes_zelda_walking_tour/__init__.py
nes_zelda_walking_tour/__main__.py
nes_zelda_walking_tour/labeled_overworldtiles.png
nes_zelda_walking_tour/link_down1.png
nes_zelda_walking_tour/link_down2.png
nes_zelda_walking_tour/link_left1.png
nes_zelda_walking_tour/link_left2.png
nes_zelda_walking_tour/link_up1.png
nes_zelda_walking_tour/link_up2.png
nes_zelda_walking_tour/overworldtiles.png
nes_zelda_walking_tour/pyganim.py
nes_zelda_walking_tour-0.1.0.dist-info/licenses/LICENSE
nes_zelda_walking_tour-0.1.0.dist-info/METADATA
nes_zelda_walking_tour-0.1.0.dist-info/WHEEL
nes_zelda_walking_tour-0.1.0.dist-info/top_level.txt
nes_zelda_walking_tour-0.1.0.dist-info/RECORD
