Metadata-Version: 2.4
Name: nes_zelda_walking_tour
Version: 0.1.0
Summary: A Pygame program to let you wander the NES Legend of Zelda overworld map.
Author-email: Your Name <your.email@example.com>
Project-URL: Homepage, https://github.com/asweigart/nes_zelda_map_data
Project-URL: Documentation, https://github.com/asweigart/nes_zelda_map_data#readme
Project-URL: Repository, https://github.com/asweigart/nes_zelda_map_data.git
Project-URL: Issues, https://github.com/asweigart/nes_zelda_map_data/issues
Keywords: example,template
Classifier: Operating System :: OS Independent
Classifier: Programming Language :: Python :: 3
Requires-Python: >=3.8
License-File: LICENSE
Requires-Dist: pygame
Dynamic: license-file
